README.md
setup.py
flask_wrappers/__init__.py
flask_wrappers/wrappers.py
flask_wrappers.egg-info/PKG-INFO
flask_wrappers.egg-info/SOURCES.txt
flask_wrappers.egg-info/dependency_links.txt
flask_wrappers.egg-info/top_level.txt