Metadata-Version: 2.1
Name: flask-wrappers
Version: 1.0.2
Summary: Decorators to facilitate flask enpoints implementation
Home-page: https://github.com/metadeta96/flask-wrappers
Author: metadeta96
Author-email: fernando.settijunior@gmail.com
License: UNKNOWN
Download-URL: https://github.com/metadeta96/flask-wrappers
Keywords: flask,decorator,route,wrapper
Platform: UNKNOWN
Classifier: Programming Language :: Python :: 3
Classifier: License :: OSI Approved :: MIT License
Classifier: Operating System :: OS Independent
Requires-Python: >=3
